kryten_playlist/__init__.py
kryten_playlist/__main__.py
kryten_playlist/admin_cmds.py
kryten_playlist/auth/__init__.py
kryten_playlist/auth/otp.py
kryten_playlist/catalog/__init__.py
kryten_playlist/catalog/cli.py
kryten_playlist/catalog/config.py
kryten_playlist/catalog/duration_fitting.py
kryten_playlist/catalog/enhanced_schema.py
kryten_playlist/catalog/enrich.py
kryten_playlist/catalog/fake_connector.py
kryten_playlist/catalog/ingest.py
kryten_playlist/catalog/markdown_export.py
kryten_playlist/catalog/mediacms_connector.py
kryten_playlist/catalog/models.py
kryten_playlist/catalog/rebuild.py
kryten_playlist/catalog/title_sanitizer.py
kryten_playlist/catalog/worker.py
kryten_playlist/catalog_refresh_watcher.py
kryten_playlist/config.py
kryten_playlist/domain/__init__.py
kryten_playlist/domain/schemas.py
kryten_playlist/marathon.py
kryten_playlist/nats/__init__.py
kryten_playlist/nats/contracts.py
kryten_playlist/nats/kv.py
kryten_playlist/queue_apply.py
kryten_playlist/service.py
kryten_playlist/storage/__init__.py
kryten_playlist/storage/catalog_repo.py
kryten_playlist/storage/schema.py
kryten_playlist/storage/sqlite.py
kryten_playlist/web/__init__.py
kryten_playlist/web/app.py
kryten_playlist/web/deps.py
kryten_playlist/web/routes/__init__.py
kryten_playlist/web/routes/auth.py
kryten_playlist/web/routes/catalog.py
kryten_playlist/web/routes/marathon.py
kryten_playlist/web/routes/nowplaying.py
kryten_playlist/web/routes/playlists.py
kryten_playlist/web/routes/queue.py
kryten_playlist/web/routes/stats.py
kryten_playlist/web/static/app.css
kryten_playlist/web/static/app.js
kryten_playlist/web/templates/apply.html
kryten_playlist/web/templates/base.html
kryten_playlist/web/templates/index.html
kryten_playlist/web/templates/login.html
kryten_playlist/web/templates/marathon.html
kryten_playlist/web/templates/playlist_editor.html
kryten_playlist/web/templates/playlists.html
kryten_playlist/web/templates/stats.html
kryten_playlist/web/ui.py
kryten_playlist-0.3.2.dist-info/entry_points.txt
kryten_playlist-0.3.2.dist-info/licenses/LICENSE
kryten_playlist-0.3.2.dist-info/METADATA
kryten_playlist-0.3.2.dist-info/WHEEL
kryten_playlist-0.3.2.dist-info/RECORD
