Metadata-Version: 2.4
Name: kryten-playlist
Version: 0.3.2
Summary: Kryten playlist management service - handles video queue, playlist operations, and catalog enrichment with LLM
License: MIT
License-File: LICENSE
Keywords: cytube,moderation,chat,nats,microservices,catalog,llm,enrichment
Author: Kryten Robot Team
Requires-Python: >=3.10,<4.0
Classifier: Development Status :: 4 - Beta
Classifier: Intended Audience :: Developers
Classifier: License :: OSI Approved :: MIT License
Classifier: Programming Language :: Python :: 3
Classifier: Programming Language :: Python :: 3.10
Classifier: Programming Language :: Python :: 3.11
Classifier: Programming Language :: Python :: 3.12
Classifier: Programming Language :: Python :: 3.13
Classifier: Programming Language :: Python :: 3.14
Classifier: Topic :: Communications :: Chat
Classifier: Topic :: Multimedia :: Video
Classifier: Topic :: Software Development :: Libraries :: Python Modules
Requires-Dist: aiosqlite (>=0.20.0,<0.21.0)
Requires-Dist: click (>=8.1.0,<9.0.0)
Requires-Dist: fastapi (>=0.115.0,<0.116.0)
Requires-Dist: httpx (>=0.27.0,<0.28.0)
Requires-Dist: jinja2 (>=3.1.4,<4.0.0)
Requires-Dist: json_repair (>=0.54.3,<0.55.0)
Requires-Dist: kryten-py (>=0.9.13)
Requires-Dist: uvicorn (>=0.30.0,<0.31.0)
Project-URL: Documentation, https://github.com/grobertson/kryten-playlist/blob/main/README.md
Project-URL: Homepage, https://github.com/grobertson/kryten-playlist
Project-URL: Repository, https://github.com/grobertson/kryten-playlist
